{
    "en": {
        "home": "home",
        "events": "events",
        "geocaches": "geocaches",
        "languageSelector": "language selector",
        "tagline": "The best geocachingBrughia website ever created"
    },
    "nl": {
        "home": "startpagina",
        "events": "evenementen",
        "geocaches": "geocaches",
        "languageSelector": "taalselector",
        "tagline": "De beste geocachingBrughia website ooit gemaakt"
      },
    "fr": {
      "home": "accueil",
      "events": "événements",
      "geocaches": "géocaches",
      "languageSelector": "sélecteur de langue",
      "tagline": "je parle pas français"
    },
    "de": {
      "home": "Startseite",
      "events": "Veranstaltungen",
      "geocaches": "Geocaches",
      "languageSelector": "Sprachauswahl",
      "tagline": "Die Über-Website von GeocachingBrughia."
    }
}